spellcast/__init__.py
spellcast/__main__.py
spellcast/dlna.py
spellcast/server.py
spellcast/spellcast.py
spellcast-0.1.0.dist-info/LICENSE
spellcast-0.1.0.dist-info/METADATA
spellcast-0.1.0.dist-info/WHEEL
spellcast-0.1.0.dist-info/entry_points.txt
spellcast-0.1.0.dist-info/top_level.txt
spellcast-0.1.0.dist-info/RECORD
