Metadata-Version: 2.1
Name: spellcast
Version: 0.1.0
Summary: Casts a video to a DLNA media renderer in the local network.
Home-page: https://github.com/lillanes/spellcast
Author: León Illanes
Author-email: lillanes@cs.toronto.edu
License: UNKNOWN
Platform: UNKNOWN
Requires-Python: >=3.7
Requires-Dist: requests (>=2.25.0)
Requires-Dist: Twisted (>=20.3.0)
